ipgs/__init__.py
ipgs/__version__.py
ipgs/core.py
ipgs-1.2.6.dist-info/licenses/LICENSE
ipgs-1.2.6.dist-info/METADATA
ipgs-1.2.6.dist-info/WHEEL
ipgs-1.2.6.dist-info/top_level.txt
ipgs-1.2.6.dist-info/RECORD
