Metadata-Version: 2.4
Name: ipgs
Version: 1.2.6
Summary: Interactive ANIMATED progress bar for Jupyter notebook projects
Author-email: Abolfazl Mohammadpour <Mohampouraz@gmail.com>
License: MIT
Project-URL: Homepage, https://pypi.org/project/ipgs/
Project-URL: Repository, https://github.com/mohampouraz/iutils/
Project-URL: Documentation, https://github.com/mohampouraz/iutils/#readme
Project-URL: BugTracker, https://github.com/mohampouraz/iutils/issues
Keywords: progressbar,jupyter,notebook,animated,ipython
Classifier: Programming Language :: Python :: 3
Classifier: Programming Language :: Python :: 3 :: Only
Classifier: Development Status :: 5 - Production/Stable
Classifier: License :: OSI Approved :: MIT License
Classifier: Intended Audience :: Developers
Classifier: Topic :: Software Development :: Libraries
Classifier: Framework :: Jupyter
Requires-Python: >=3.8
License-File: LICENSE
Dynamic: license-file
